[

    { 
        "ServerName":"ABC",
        "ServiceName":"Adobe",
        "ServiceStatus":"Running"
        },
        {
        "ServerName":"ABCasdf",
        "ServiceName":"ApHIdMOntoriservice",
        "ServiceStatus":"Running"
        },
        {
        "ServerName":"ABC",
        "ServiceName":"AppINfo",
        "ServiceStatus":"Stopped"
        },
        {
            "ServerName":"ABCasdf",
            "ServiceName":"ApHIdMOntoriservice",
            "ServiceStatus":"Running"
            },
            {
                "ServerName":"ABCasdf",
                "ServiceName":"ApHIdMOntoriservice",
                "ServiceStatus":"Running"
                },
                {
                    "ServerName":"ABCasdf",
                    "ServiceName":"ApHIdMOntoriservice",
                    "ServiceStatus":"Running"
                    },
                    {
                        "ServerName":"ABCasdf",
                        "ServiceName":"ApHIdMOntoriservice",
                        "ServiceStatus":"Running"
                        },
                        {
                            "ServerName":"ABCasdf",
                            "ServiceName":"ApHIdMOntoriservice",
                            "ServiceStatus":"Running"
                            },
                            {
                                "ServerName":"ABCasdf",
                                "ServiceName":"ApHIdMOntoriservice",
                                "ServiceStatus":"Running"
                                }
]